pcsv/__init__.py
pcsv/compat2.py
pcsv/compat3.py
pcsv/concatenate.py
pcsv/csv_file.py
pcsv/dsort.py
pcsv/merge.py
pcsv/pkgdata.py
pcsv/ptypes.py
pcsv/replace.py
pcsv/write.py
pcsv-1.0.8.dist-info/METADATA
pcsv-1.0.8.dist-info/RECORD
pcsv-1.0.8.dist-info/WHEEL
pcsv-1.0.8.dist-info/top_level.txt
