Metadata-Version: 2.1
Name: pcsv
Version: 1.0.8
Summary: UNKNOWN
Home-page: http://github.com/pmacosta/pcsv/
Author: Pablo Acosta-Serafini
Author-email: pmasdev@gmail.com
License: MIT
Platform: any
Classifier: Programming Language :: Python :: 2.7
Classifier: Programming Language :: Python :: 3.5
Classifier: Programming Language :: Python :: 3.6
Classifier: Programming Language :: Python :: 3.7
Classifier: Development Status :: 5 - Production/Stable
Classifier: Natural Language :: English
Classifier: Environment :: Console
Classifier: Intended Audience :: Developers
Classifier: License :: OSI Approved :: MIT License
Classifier: Operating System :: OS Independent
Classifier: Topic :: Software Development :: Libraries :: Python Modules
Requires-Dist: pycontracts (>=1.8.2)
Requires-Dist: pmisc (>=1.5.8)
Requires-Dist: pexdoc (>=1.1.4)
